gwBOB/BOB_terms.py
gwBOB/BOB_terms_jax.py
gwBOB/BOB_utils.py
gwBOB/__init__.py
gwBOB/ascii_funcs.py
gwBOB/convert_to_strain_using_series.py
gwBOB/gen_utils.py
gwBOB/mismatch_utils.py
gwbob-1.0.2.dist-info/licenses/LICENSE
gwbob-1.0.2.dist-info/METADATA
gwbob-1.0.2.dist-info/WHEEL
gwbob-1.0.2.dist-info/top_level.txt
gwbob-1.0.2.dist-info/RECORD
