Metadata-Version: 2.4
Name: gwBOB
Version: 1.0.2
Summary: A Backwards-One-Body Gravitational Waveform Package
Author-email: Anuj Kankani <anuj.kankani@mail.wvu.edu>
License: MIT
Project-URL: Homepage, https://github.com/AnujKankani/BackwardsOneBody
Project-URL: Documentation, https://backwardsonebody.readthedocs.io
Project-URL: Repository, https://github.com/AnujKankani/BackwardsOneBody
Requires-Python: >=3.10
License-File: LICENSE
Requires-Dist: sxs
Requires-Dist: kuibit
Requires-Dist: sympy
Requires-Dist: qnmfits
Requires-Dist: jax
Provides-Extra: docs
Requires-Dist: sphinx; extra == "docs"
Requires-Dist: sphinx-rtd-theme; extra == "docs"
Requires-Dist: myst-parser; extra == "docs"
Requires-Dist: sphinx-autodoc-typehints; extra == "docs"
Requires-Dist: sphinx-copybutton; extra == "docs"
Requires-Dist: sphinx-design; extra == "docs"
Provides-Extra: tests
Requires-Dist: pytest; extra == "tests"
Dynamic: license-file
